rpa_shein/__init__.py
rpa_shein/api/BillApi.py
rpa_shein/api/ShopAmount.py
rpa_shein/api/__init__.py
rpa_shein/api/base.py
rpa_shein/command/__init__.py
rpa_shein/command/bill/AnalysisBill.py
rpa_shein/command/bill/__init__.py
rpa_shein/command/bill/service/__init__.py
rpa_shein/command/temporary_auth/__init__.py
rpa_shein/command/temporary_auth/user_token.py
rpa_shein/request/__init__.py
rpa_shein/service/SheinService.py
rpa_shein/service/__init__.py
rpa_shein-1.0.1.dist-info/LICENSE
rpa_shein-1.0.1.dist-info/METADATA
rpa_shein-1.0.1.dist-info/WHEEL
rpa_shein-1.0.1.dist-info/top_level.txt
rpa_shein-1.0.1.dist-info/RECORD
