Metadata-Version: 2.1
Name: rpa_shein
Version: 1.0.1
Summary: RPA automated execution program for Shein
Home-page: https://pypi.org/project/rpa-shein/
Author: Zhongshuizhou
Author-email: zhongshuizhou@qq.com
Classifier: Programming Language :: Python :: 3.8
Classifier: License :: OSI Approved :: MIT License
Classifier: Operating System :: OS Independent
Requires-Python: >=3.8
License-File: LICENSE
Requires-Dist: selenium==4.27.1
Requires-Dist: PyExecJS==1.5.1
